{
  "parent": "minecraft:block/block",
  "render_type": "cutout",
  "textures": {
    "conduit": "beemancer:block/iron",
    "crystal": "beemancer:block/altar/crystal_altar",
    "particle": "beemancer:block/iron"
  },
  "elements": [
    {
      "name": "Main Body",
      "from": [3, 6, 10],
      "to": [13, 16, 16],
      "faces": {
        "north": {"texture": "#conduit", "uv": [3, 3, 13, 13]},
        "east": {"texture": "#conduit", "uv": [0, 3, 6, 13]},
        "south": {"texture": "#conduit", "uv": [3, 3, 13, 13]},
        "west": {"texture": "#conduit", "uv": [0, 3, 6, 13]},
        "up": {"texture": "#conduit", "uv": [3, 0, 13, 6]},
        "down": {"texture": "#conduit", "uv": [3, 0, 13, 6]}
      }
    },
    {
      "from": [3, 8, 0],
      "to": [19, 8, 16],
      "rotation": {"angle": -45, "axis": "z", "origin": [8, 8, 11], "rescale": false},
      "faces": {
        "east": {"uv": [0, 0, 16, 16], "texture": "#crystal"},
        "west": {"uv": [0, 0, 16, 16], "texture": "#crystal"}
      }
    },
    {
      "from": [3, 8, 0],
      "to": [19, 8, 16],
      "rotation": {"angle": -45, "axis": "z", "origin": [8, 8, 11], "rescale": false},
      "faces": {
        "up": {"uv": [0, 0, 16, 16], "texture": "#crystal"},
        "down": {"uv": [0, 0, 16, 16], "texture": "#crystal"}
      }
    }
  ]
}
