{
  "parent": "minecraft:block/block",
  "render_type": "translucent",
  "textures": {
    "gold": "minecraft:block/gold_block",
    "reservoir": "beemancer:block/alchemy/alembic_glass",
    "particle": "beemancer:block/building/honeyed_glass"
  },
  "elements": [
    {
      "name": "Glass",
      "from": [2, 4, 2],
      "to": [14, 24, 14],
      "faces": {
        "north": {"texture": "#reservoir", "uv": [0,0,12,16]},
        "east": {"texture": "#reservoir", "uv": [0,0,12,16]},
        "south": {"texture": "#reservoir", "uv": [0,0,12,16]},
        "west": {"texture": "#reservoir", "uv": [0,0,12,16]}
      }
    },
    {
      "name": "Bottom",
      "from": [1, 2, 1],
      "to": [15, 4, 15],
      "faces": {
        "north": {"texture": "#gold"},
        "east": {"texture": "#gold"},
        "south": {"texture": "#gold"},
        "west": {"texture": "#gold"},
        "up": {"texture": "#gold"},
        "down": {"texture": "#gold"}
      }
    },
    {
      "name": "Top",
      "from": [1, 24, 1],
      "to": [15, 26, 15],
      "faces": {
        "north": {"texture": "#gold", "uv": [1,13,15,15]},
        "east": {"texture": "#gold", "uv": [1,13,15,15]},
        "south": {"texture": "#gold", "uv": [1,13,15,15]},
        "west": {"texture": "#gold", "uv": [1,13,15,15]},
        "up": {"texture": "#gold"},
        "down": {"texture": "#gold"}
      }
    }
  ]
}
